fstats/__init__.py
fstats/__main__.py
fstats-0.40.dist-info/METADATA
fstats-0.40.dist-info/WHEEL
fstats-0.40.dist-info/entry_points.txt
fstats-0.40.dist-info/top_level.txt
fstats-0.40.dist-info/RECORD
