Metadata-Version: 2.1
Name: fstats
Version: 0.40
Summary: UNKNOWN
Home-page: UNKNOWN
Author: bbing
License: UNKNOWN
Platform: UNKNOWN
Requires-Dist: psutil
